fp_xls_2_xml/__init__.py
fp_xls_2_xml/__main__.py
fp_xls_2_xml/cli.py
fp_xls_2_xml/convertors.py
fp_xls_2_xml/fpxls2xml.py
fp_xls_2_xml/processors.py
fp_xls_2_xml-1.0.1.dist-info/LICENSE.txt
fp_xls_2_xml-1.0.1.dist-info/METADATA
fp_xls_2_xml-1.0.1.dist-info/WHEEL
fp_xls_2_xml-1.0.1.dist-info/entry_points.txt
fp_xls_2_xml-1.0.1.dist-info/top_level.txt
fp_xls_2_xml-1.0.1.dist-info/RECORD
