Metadata-Version: 2.1
Name: fp-xls-2-xml
Version: 1.0.1
Summary: UNKNOWN
Home-page: UNKNOWN
License: UNKNOWN
Platform: UNKNOWN
Requires-Python: >=3.5.*
Requires-Dist: certifi (==2019.9.11)
Requires-Dist: chardet (==3.0.4)
Requires-Dist: dataclasses (==0.6)
Requires-Dist: docutils (==0.15.2)
Requires-Dist: et-xmlfile (==1.0.1)
Requires-Dist: fire (==0.2.1)
Requires-Dist: idna (==2.8)
Requires-Dist: jdcal (==1.4.1)
Requires-Dist: numpy (==1.17.4)
Requires-Dist: pandas (==0.25.3)
Requires-Dist: pygments (==2.4.2)
Requires-Dist: python-dateutil (==2.8.1)
Requires-Dist: pytz (==2019.3)
Requires-Dist: requests (==2.22.0)
Requires-Dist: six (==1.13.0)
Requires-Dist: termcolor (==1.1.0)
Requires-Dist: urllib3 (==1.25.7)
Requires-Dist: xlrd (==1.2.0)
Requires-Dist: xlwt (==1.3.0)
